[
    {
        "type": "textGroup",
        "groupStyle": [
            "mb-5"
        ],
        "textStyle": [
            "has-text-centered",
            "has-text-weight-bold",
            "mb-1"
        ],
        "text": [
            "न च तस्मान्मनुष्येषु कश्चिन्मे प्रियकृत्तम: ।",
            "भविता न च मे तस्मादन्य: प्रियतरो भुवि ॥ ६९ ॥"
        ]
    },
    {
        "type": "textGroup",
        "groupStyle": [
            "mb-5"
        ],
        "textStyle": [
            "has-text-centered",
            "is-italic",
            "mb-1"
        ],
        "text": [
            "na ca tasmān manuṣyeṣu",
            "kaścin me priya-kṛttamaḥ",
            "bhavitā na ca me tasmād",
            "anyaḥ priya-taro bhuvi"
        ]
    },
    {
        "type": "textGroup",
        "groupStyle": [
            "mb-3"
        ],
        "textStyle": [
            "has-text-centered",
            "has-text-weight-bold"
        ],
        "text": [
            "Synonyms"
        ]
    },
    {
        "type": "textGroup",
        "groupStyle": [
            "mb-5"
        ],
        "textStyle": [
            "has-text-justified"
        ],
        "text": [
            "**na** — never; **ca** — and; **tasmāt** — than him; **manuṣyeṣu** — among men; **kaścit** — anyone; **me** — to Me; **priya**-**kṛt**-**tamaḥ** — more dear; **bhavitā** — will become; **na** — nor; **ca** — and; **me** — to Me; **tasmāt** — than him; **anyaḥ** — another; **priya**-**taraḥ** — dearer; **bhuvi** — in this world."
        ]
    },
    {
        "type": "textGroup",
        "groupStyle": [
            "mb-3"
        ],
        "textStyle": [
            "has-text-centered",
            "has-text-weight-bold"
        ],
        "text": [
            "Translation"
        ]
    },
    {
        "type": "textGroup",
        "groupStyle": [
            "mb-5"
        ],
        "textStyle": [
            "has-text-justified"
        ],
        "text": [
            "There is no servant in this world more dear to Me than he, nor will there ever be one more dear."
        ]
    }
]